box2csv/__init__.py
box2csv/cldf.py
box2csv/cli.py
box2csv/helpers.py
box2csv/data/interlinear_config.yaml
box2csv/data/shoebox.yaml
box2csv/data/toolbox.yaml
box2csv-0.0.1.dist-info/LICENSE
box2csv-0.0.1.dist-info/METADATA
box2csv-0.0.1.dist-info/WHEEL
box2csv-0.0.1.dist-info/entry_points.txt
box2csv-0.0.1.dist-info/top_level.txt
box2csv-0.0.1.dist-info/RECORD
