Metadata-Version: 2.1
Name: box2csv
Version: 0.0.1
Summary: Extract shoebox and toolbox data to CSV files.
Home-page: https://github.com/fmatter/box2csv
Author: Florian Matter
Author-email: florianmatter@gmail.com
Project-URL: Bug Tracker, https://github.com/fmatter/box2csv/issues
Keywords: shoebox,toolbox
Classifier: Development Status :: 2 - Pre-Alpha
Classifier: Intended Audience :: Science/Research
Classifier: License :: OSI Approved :: Apache Software License
Classifier: Natural Language :: English
Classifier: Programming Language :: Python :: 3
Classifier: Programming Language :: Python :: 3.7
Classifier: Programming Language :: Python :: 3.8
Classifier: Programming Language :: Python :: 3.9
Classifier: Programming Language :: Python :: 3.10
License-File: LICENSE
Requires-Dist: colorlog
Requires-Dist: click
Requires-Dist: pandas (>=1.3.5)
Requires-Dist: python-slugify (>=6.1.2)
Requires-Dist: cldfbench (>=1.13.0)
Requires-Dist: pycldf (>=1.29.0)
Requires-Dist: importlib-resources (>=5.10.0)
Provides-Extra: dev
Requires-Dist: bump2version ; extra == 'dev'
Requires-Dist: coverage[toml] ; extra == 'dev'
Requires-Dist: prospector[with_pyroma] (==1.7.7) ; extra == 'dev'
Requires-Dist: isort ; extra == 'dev'
Requires-Dist: pytest ; extra == 'dev'
Requires-Dist: pytest-cov ; extra == 'dev'
Requires-Dist: sphinx ; extra == 'dev'
Requires-Dist: sphinx-rtd-theme ; extra == 'dev'
Requires-Dist: sphinx-autoapi ; extra == 'dev'
Requires-Dist: sphinxcontrib-napoleon ; extra == 'dev'
Requires-Dist: tox ; extra == 'dev'
Requires-Dist: myst-parser ; extra == 'dev'
Requires-Dist: flake8 ; extra == 'dev'
Requires-Dist: twine ; extra == 'dev'
Requires-Dist: jinja2 ; extra == 'dev'
Requires-Dist: keepachangelog ; extra == 'dev'
Provides-Extra: publishing
Requires-Dist: twine ; extra == 'publishing'
Requires-Dist: wheel ; extra == 'publishing'
